{
  "apiVersion": "v1",
  "kind": "Service",
  "metadata": {
    "annotations": {
      "kubectl.kubernetes.io/last-applied-configuration": "{\"apiVersion\":\"v1\",\"kind\":\"Service\",\"metadata\":{\"annotations\":{},\"name\":\"bac-marketplace\",\"namespace\":\"dev-ben\"},\"spec\":{\"internalTrafficPolicy\":\"Cluster\",\"ipFamilies\":[\"IPv4\"],\"ipFamilyPolicy\":\"SingleStack\",\"ports\":[{\"port\":9015,\"protocol\":\"TCP\",\"targetPort\":9015}],\"selector\":{\"app\":\"bac-marketplace\"},\"sessionAffinity\":\"None\",\"type\":\"ClusterIP\"}}\n"
    },
    "name": "bac-marketplace",
    "namespace": "dev-ben"
  },
  "spec": {
    "clusterIP": "10.43.212.156",
    "clusterIPs": [
      "10.43.212.156"
    ],
    "internalTrafficPolicy": "Cluster",
    "ipFamilies": [
      "IPv4"
    ],
    "ipFamilyPolicy": "SingleStack",
    "ports": [
      {
        "port": 9015,
        "protocol": "TCP",
        "targetPort": 9015
      }
    ],
    "selector": {
      "app": "bac-marketplace"
    },
    "sessionAffinity": "None",
    "type": "ClusterIP"
  }
}